{
  "Alphabets":  [
    {"name": "A", "path": "assets/videos/alphabets/A.mp4"},
    {"name": "B", "path": "assets/videos/alphabets/B.mp4"},
    {"name": "C", "path": "assets/videos/alphabets/C.mp4"},
    {"name": "D", "path": "assets/videos/alphabets/D.mp4"},
    {"name": "E", "path": "assets/videos/alphabets/E.mp4"},
    {"name": "F", "path": "assets/videos/alphabets/F.mp4"},
    {"name": "G", "path": "assets/videos/alphabets/G.mp4"},
    {"name": "H", "path": "assets/videos/alphabets/H.mp4"},
    {"name": "I", "path": "assets/videos/alphabets/I.mp4"},
    {"name": "J", "path": "assets/videos/alphabets/J.mp4"},
    {"name": "K", "path": "assets/videos/alphabets/K.mp4"},
    {"name": "M", "path": "assets/videos/alphabets/M.mp4"},
    {"name": "N", "path": "assets/videos/alphabets/N.mp4"},
    {"name": "L", "path": "assets/videos/alphabets/L.mp4"},
    {"name": "O", "path": "assets/videos/alphabets/O.mp4"},
    {"name": "P", "path": "assets/videos/alphabets/P.mp4"},
    {"name": "Q", "path": "assets/videos/alphabets/Q.mp4"},
    {"name": "R", "path": "assets/videos/alphabets/R.mp4"},
    {"name": "S", "path": "assets/videos/alphabets/S.mp4"},
    {"name": "T", "path": "assets/videos/alphabets/T.mp4"},
    {"name": "U", "path": "assets/videos/alphabets/U.mp4"},
    {"name": "V", "path": "assets/videos/alphabets/V.mp4"},
    {"name": "W", "path": "assets/videos/alphabets/W.mp4"},
    {"name": "X", "path": "assets/videos/alphabets/X.mp4"},
    {"name": "Y", "path": "assets/videos/alphabets/Y.mp4"},
    {"name": "Z", "path": "assets/videos/alphabets/Z.mp4"}
  ],
  "Words": [
      {"name": "After", "path": "assets/videos/words/After.mp4"},
        {"name": "Again", "path": "assets/videos/words/Again.mp4"},
        {"name": "Against", "path": "assets/videos/words/Against.mp4"},
        {"name": "Age", "path": "assets/videos/words/Age.mp4"},
        {"name": "All", "path": "assets/videos/words/All.mp4"},
        {"name": "Alone", "path": "assets/videos/words/Alone.mp4"},
        {"name": "Also", "path": "assets/videos/words/Also.mp4"},
        {"name": "And", "path": "assets/videos/words/And.mp4"},
        {"name": "Ask", "path": "assets/videos/words/Ask.mp4"},
        {"name": "At", "path": "assets/videos/words/At.mp4"},
        {"name": "Be", "path": "assets/videos/words/Be.mp4"},
        {"name": "Beautiful", "path": "assets/videos/words/Beautiful.mp4"},
        {"name": "Before", "path": "assets/videos/words/Before.mp4"},
        {"name": "Best", "path": "assets/videos/words/Best.mp4"},
        {"name": "Better", "path": "assets/videos/words/Better.mp4"},
        {"name": "Busy", "path": "assets/videos/words/Busy.mp4"},
        {"name": "But", "path": "assets/videos/words/But.mp4"},
        {"name": "Bye", "path": "assets/videos/words/Bye.mp4"},
        {"name": "Can", "path": "assets/videos/words/Can.mp4"},
        {"name": "Cannot", "path": "assets/videos/words/Cannot.mp4"},
        {"name": "Change", "path": "assets/videos/words/Change.mp4"},
        {"name": "College", "path": "assets/videos/words/College.mp4"},
        {"name": "Come", "path": "assets/videos/words/Come.mp4"},
        {"name": "Computer", "path": "assets/videos/words/Computer.mp4"},
        {"name": "Day", "path": "assets/videos/words/Day.mp4"},
        {"name": "Distance", "path": "assets/videos/words/Distance.mp4"},
        {"name": "Do Not", "path": "assets/videos/words/Do_Not.mp4"},
        {"name": "Do", "path": "assets/videos/words/Do.mp4"},
        {"name": "Does Not", "path": "assets/videos/words/Does_Not.mp4"},
        {"name": "Eat", "path": "assets/videos/words/Eat.mp4"},
        {"name": "Engineer", "path": "assets/videos/words/Engineer.mp4"},
        {"name": "Fight", "path": "assets/videos/words/Fight.mp4"},
        {"name": "Finish", "path": "assets/videos/words/Finish.mp4"},
        {"name": "From", "path": "assets/videos/words/From.mp4"},
        {"name": "Glitter", "path": "assets/videos/words/Glitter.mp4"},
        {"name": "Go", "path": "assets/videos/words/Go.mp4"},
        {"name": "God", "path": "assets/videos/words/God.mp4"},
        {"name": "Gold", "path": "assets/videos/words/Gold.mp4"},
        {"name": "Good", "path": "assets/videos/words/Good.mp4"},
        {"name": "Great", "path": "assets/videos/words/Great.mp4"},
        {"name": "Hand", "path": "assets/videos/words/Hand.mp4"},
        {"name": "Hands", "path": "assets/videos/words/Hands.mp4"},
        {"name": "Happy", "path": "assets/videos/words/Happy.mp4"},
        {"name": "Hello", "path": "assets/videos/words/Hello.mp4"},
        {"name": "Help", "path": "assets/videos/words/Help.mp4"},
        {"name": "Her", "path": "assets/videos/words/Her.mp4"},
        {"name": "Here", "path": "assets/videos/words/Here.mp4"},
        {"name": "His", "path": "assets/videos/words/His.mp4"},
        {"name": "Home", "path": "assets/videos/words/Home.mp4"},
        {"name": "Homepage", "path": "assets/videos/words/Homepage.mp4"},
        {"name": "How", "path": "assets/videos/words/How.mp4"},
        {"name": "Invent", "path": "assets/videos/words/Invent.mp4"},
        {"name": "It", "path": "assets/videos/words/It.mp4"},
        {"name": "Keep", "path": "assets/videos/words/Keep.mp4"},
        {"name": "Language", "path": "assets/videos/words/Language.mp4"},
        {"name": "Laugh", "path": "assets/videos/words/Laugh.mp4"},
        {"name": "Learn", "path": "assets/videos/words/Learn.mp4"},
        {"name": "Me", "path": "assets/videos/words/Me.mp4"},
        {"name": "More", "path": "assets/videos/words/More.mp4"},
        {"name": "My", "path": "assets/videos/words/My.mp4"},
        {"name": "Name", "path": "assets/videos/words/Name.mp4"},
        {"name": "Next", "path": "assets/videos/words/Next.mp4"},
        {"name": "Not", "path": "assets/videos/words/Not.mp4"},
        {"name": "Now", "path": "assets/videos/words/Now.mp4"},
        {"name": "Of", "path": "assets/videos/words/Of.mp4"},
        {"name": "On", "path": "assets/videos/words/On.mp4"},
        {"name": "Our", "path": "assets/videos/words/Our.mp4"},
        {"name": "Out", "path": "assets/videos/words/Out.mp4"},
        {"name": "Pretty", "path": "assets/videos/words/Pretty.mp4"},
        {"name": "Right", "path": "assets/videos/words/Right.mp4"},
        {"name": "Sad", "path": "assets/videos/words/Sad.mp4"},
        {"name": "Safe", "path": "assets/videos/words/Safe.mp4"},
        {"name": "See", "path": "assets/videos/words/See.mp4"},
        {"name": "Self", "path": "assets/videos/words/Self.mp4"},
        {"name": "Sign", "path": "assets/videos/words/Sign.mp4"},
        {"name": "Sing", "path": "assets/videos/words/Sing.mp4"},
        {"name": "So", "path": "assets/videos/words/So.mp4"},
        {"name": "Sound", "path": "assets/videos/words/Sound.mp4"},
        {"name": "Stay", "path": "assets/videos/words/Stay.mp4"},
        {"name": "Study", "path": "assets/videos/words/Study.mp4"},
        {"name": "Talk", "path": "assets/videos/words/Talk.mp4"},
        {"name": "Television", "path": "assets/videos/words/Television.mp4"},
        {"name": "Thank You", "path": "assets/videos/words/Thank_You.mp4"},
        {"name": "Thank", "path": "assets/videos/words/Thank.mp4"},
        {"name": "That", "path": "assets/videos/words/That.mp4"},
        {"name": "They", "path": "assets/videos/words/They.mp4"},
        {"name": "This", "path": "assets/videos/words/This.mp4"},
        {"name": "Those", "path": "assets/videos/words/Those.mp4"},
        {"name": "Time", "path": "assets/videos/words/Time.mp4"},
        {"name": "To", "path": "assets/videos/words/To.mp4"},
        {"name": "Type", "path": "assets/videos/words/Type.mp4"},
        {"name": "Us", "path": "assets/videos/words/Us.mp4"},
        {"name": "Walk", "path": "assets/videos/words/Walk.mp4"},
        {"name": "Wash", "path": "assets/videos/words/Wash.mp4"}
  ],
    "Sentence Formation": [
      {"name": "After", "path": "assets/videos/words/After.mp4"},
      {"name": "Again", "path": "assets/videos/words/Again.mp4"},
      {"name": "Against", "path": "assets/videos/words/Against.mp4"}
    ],
  "Numbers": [
    {"name": "0", "path": "assets/videos/numbers/0.mp4"},
    {"name": "1", "path": "assets/videos/numbers/1.mp4"},
    {"name": "2", "path": "assets/videos/numbers/2.mp4"},
    {"name": "3", "path": "assets/videos/numbers/3.mp4"},
    {"name": "4", "path": "assets/videos/numbers/4.mp4"},
    {"name": "5", "path": "assets/videos/numbers/5.mp4"},
    {"name": "6", "path": "assets/videos/numbers/6.mp4"},
    {"name": "7", "path": "assets/videos/numbers/7.mp4"},
    {"name": "8", "path": "assets/videos/numbers/8.mp4"},
    {"name": "9", "path": "assets/videos/numbers/9.mp4"}
  ]
}